bedrock_region_balancer/__init__.py
bedrock_region_balancer/auth_types.py
bedrock_region_balancer/balancer.py
bedrock_region_balancer/client.py
bedrock_region_balancer/converse_api.py
bedrock_region_balancer/exceptions.py
bedrock_region_balancer/model_mappings.py
bedrock_region_balancer/secrets_manager.py
bedrock_region_balancer-0.5.0.dist-info/licenses/LICENSE
tests/__init__.py
tests/test_batch_processing.py
tests/test_batch_simple.py
tests/test_comprehensive.py
bedrock_region_balancer-0.5.0.dist-info/METADATA
bedrock_region_balancer-0.5.0.dist-info/WHEEL
bedrock_region_balancer-0.5.0.dist-info/top_level.txt
bedrock_region_balancer-0.5.0.dist-info/RECORD
