Metadata-Version: 2.4
Name: bedrock-region-balancer
Version: 0.5.0
Summary: AWS Bedrock region load balancer with round-robin distribution and batch processing
Author: SungHyon Kim
Author-email: SungHyon Kim <spero84@gmail.com>
License: MIT
Project-URL: Homepage, https://github.com/spero84/bedrock-region-balancer
Project-URL: Bug Reports, https://github.com/spero84/bedrock-region-balancer/issues
Project-URL: Source, https://github.com/spero84/bedrock-region-balancer
Keywords: aws,bedrock,load-balancer,round-robin,ai,llm
Classifier: Development Status :: 3 - Alpha
Classifier: Intended Audience :: Developers
Classifier: Topic :: Software Development :: Libraries :: Python Modules
Classifier: License :: OSI Approved :: MIT License
Classifier: Programming Language :: Python :: 3
Classifier: Programming Language :: Python :: 3.9
Classifier: Programming Language :: Python :: 3.10
Classifier: Programming Language :: Python :: 3.11
Requires-Python: >=3.8
License-File: LICENSE
Requires-Dist: boto3>=1.33.0
Requires-Dist: botocore>=1.33.0
Requires-Dist: python-dotenv>=1.0.0
Provides-Extra: dev
Requires-Dist: pytest>=7.0.0; extra == "dev"
Requires-Dist: pytest-asyncio>=0.21.0; extra == "dev"
Requires-Dist: pytest-cov>=4.0.0; extra == "dev"
Requires-Dist: black>=23.0.0; extra == "dev"
Requires-Dist: flake8>=6.0.0; extra == "dev"
Requires-Dist: mypy>=1.0.0; extra == "dev"
Requires-Dist: boto3-stubs[bedrock,bedrock-runtime,secretsmanager]>=1.28.0; extra == "dev"
Requires-Dist: python-dotenv>=1.0.0; extra == "dev"
Dynamic: author
Dynamic: license-file
Dynamic: requires-python
